{
    "作者": "",
    "站名": "柒月影视",
    //"首页": "电影",
     "请求头": "User-Agent$okhttp/3.12.0",
     //fabuhttps://www.iptv.cc//api.php/v1.vod
    "分类": "电影&电视剧&综艺",
    "分类值": "1&2&3",
    "分类url": "https://www.9day.cc/api.php/app/video?tid={cateId}&class={class}&area={area}&pg={catePg}",
    "数组二次截取": "data\":[&&]",
    "数组": "{&&}",
    "图片": "vod_pic\"*\"&&\"",
    "标题": "vod_name\"*\"&&\"",
    "副标题": "vod_remarks\"*\"&&\"",
    "链接": "https://www.9day.cc/api.php/app/video_detail?id=+vod_id\":&&,",
    "搜索url": "https://www.9day.cc/api.php/app/search?text={wd}",
    "搜索模式": "1",
    "搜索二次截取": "data\":[&&]",
    "搜索数组": "{&&}",
    "搜索图片": "vod_pic\"*\"&&\"",
    "搜索标题": "vod_name\"*\"&&\"",
    "搜索副标题": "vod_remarks\"*\"&&\"",
    "搜索链接": "https://www.9day.cc/api.php/app/video_detail?id=+vod_id\":&&,",
    "影片类型": "vod_class\"*\"&&\"",
    "导演": "vod_director\"*\"&&\"",
    "主演": "vod_actor\"*\"&&\"",
    "简介": "vod_content\"*\"&&\"",
    "线路数组": "{\"name\":&&,",
    "线路标题": "\"&&\"",
    "播放数组": "\"url\":&&,[替换:\">>链表题#$>>题链#\\#>>链表表题]",
    "播放二次截取": "",
    "播放列表": "表&&表",
    "播放标题": "题&&题",
    "跳转解析": "柒月$https://jiexi.xn--654a.cc/home/api?type=ys&uid=12199190&key=adeilprsLPSU034578&url=#柒月②号$https://ff.imayday.cn/api/?key=R0f1mwIXkH3nx1pv8W&url=#腾讯$http://vip.xiaomaomi.tv/api.php?key=behkwyABCEKNOSU369&url=#爱奇艺$http://vip.xiaomaomi.tv/api.php?key=behkwyABCEKNOSU369&url=#优酷$http://vip.xiaomaomi.tv/api.php?key=behkwyABCEKNOSU369&url=#芒果$http://vip.xiaomaomi.tv/api.php?key=behkwyABCEKNOSU369&url=[替换:url\": \">>url\":\"]",
    "播放链接": "解析+链&&链",
     "跳转播放链接": "https+https&&\"",
    //"播放链接前缀": "https",
    "嗅探词":"m3u8?Expires#data.aliyundrive.net#.m3u8#.mp4#.flv#.mp3#.m4a",
    "过滤词":"51.la#cnzz.com#baidu.com#bilibili.com",
    "播放请求头":"User-Agent$123",
    //"免嗅":"1",
     "筛选":{
"1":[
  {"key":"class","name":"类型","value":[
{"n":"全部","v":""},
{"n":"动作片","v":"动作"},
{"n":"喜剧片","v":"喜剧"},
{"n":"爱情片","v":"爱情"},
{"n":"科幻片","v":"科幻"},
{"n":"恐怖片","v":"恐怖"},
{"n":"剧情片","v":"剧情"},
{"n":"冒险片","v":"冒险"},
{"n":"悬疑","v":"悬疑"}]},
  
  {"key":"area","name":"地区","value":[
  {"n":"全部","v":""},
  {"n":"大陆","v":"中国大陆"},
  {"n":"香港","v":"中国香港"},
  {"n":"韩国","v":"韩国"},
  {"n":"美国","v":"美国"},
  {"n":"日本","v":"日本"},
  {"n":"法国","v":"法国"},
  {"n":"英国","v":"英国"},
  {"n":"德国","v":"德国"},
  {"n":"台湾","v":"中国台湾"},
  {"n":"泰国","v":"泰国"},
  {"n":"印度","v":"印度"},
  {"n":"其他","v":"其他"}]},
  
  {"key":"year","name":"年份","value":[
  {"n":"全部","v":""},
  {"n":"2023","v":"2023"},
  {"n":"2022","v":"2022"},
  {"n":"2021","v":"2021"},
  {"n":"2020","v":"2020"},
  {"n":"2019","v":"2019"},
  {"n":"2018","v":"2018"},
  {"n":"2017","v":"2017"},
  {"n":"2016","v":"2016"},
  {"n":"2015","v":"2015"},
  {"n":"2014","v":"2014"},
  {"n":"2013","v":"2013"},
  {"n":"2012","v":"2012"},
  {"n":"2011","v":"2011"},
  {"n":"2010","v":"2010"},
  {"n":"2009","v":"2009"},
  {"n":"2008","v":"2008"},
  {"n":"2006","v":"2006"},
  {"n":"2005","v":"2005"},
  {"n":"2004","v":"2004"}]}],
"2":[
  {"key":"class","name":"剧情","value":[
  {"n":"全部","v":""},
  {"n":"喜剧","v":"喜剧"},
  {"n":"古装","v":"古装"},
  {"n":"恐怖","v":"恐怖"},
  {"n":"动作","v":"动作"},
  {"n":"科幻","v":"科幻"},
  {"n":"剧情","v":"剧情"},
  {"n":"犯罪","v":"犯罪"},
  {"n":"奇幻","v":"奇幻"},
  {"n":"冒险","v":"冒险"},
  {"n":"奈飞","v":"Netflix"},
  {"n":"悬疑","v":"悬疑"},
  {"n":"惊悚","v":"惊悚"}]},
  
  {"key":"area","name":"地区","value":[
  {"n":"全部","v":""},
  {"n":"中国","v":"中国大陆"},
  {"n":"香港","v":"中国香港"},
  {"n":"台湾","v":"中国台湾"},
  {"n":"美国","v":"美国"},
  {"n":"法国","v":"法国"},
  {"n":"英国","v":"英国"},
  {"n":"韩国","v":"韩国"},
  {"n":"其他","v":"其他"}]},
  
  {"key":"year","name":"年份","value":[
  {"n":"全部","v":""},
  {"n":"2023","v":"2023"},
  {"n":"2022","v":"2022"},
  {"n":"2021","v":"2021"},
  {"n":"2020","v":"2020"},
  {"n":"2019","v":"2019"},
  {"n":"2018","v":"2018"},
  {"n":"2017","v":"2017"},
  {"n":"2016","v":"2016"},
  {"n":"2015","v":"2015"},
  {"n":"2014","v":"2014"},
  {"n":"2013","v":"2013"},
  {"n":"2012","v":"2012"},
  {"n":"2011","v":"2011"},
  {"n":"2010","v":"2010"}]}]
}
}